pg_analyse/__init__.py
pg_analyse/cli.py
pg_analyse/formatters.py
pg_analyse/settings.py
pg_analyse/toolbox.py
pg_analyse/inspections/__init__.py
pg_analyse/inspections/base.py
pg_analyse/inspections/bundled.py
pg_analyse/inspections/contrib/__init__.py
pg_analyse/inspections/contrib/index_health/__init__.py
pg_analyse/inspections/contrib/index_health/inspections.py
pg_analyse/sql/contrib/index_health/.git
pg_analyse/sql/contrib/index_health/LICENSE
pg_analyse/sql/contrib/index_health/README.md
pg_analyse/sql/contrib/index_health/sql/bloated_indexes.sql
pg_analyse/sql/contrib/index_health/sql/bloated_tables.sql
pg_analyse/sql/contrib/index_health/sql/duplicated_indexes.sql
pg_analyse/sql/contrib/index_health/sql/foreign_keys_without_index.sql
pg_analyse/sql/contrib/index_health/sql/indexes_with_null_values.sql
pg_analyse/sql/contrib/index_health/sql/intersected_indexes.sql
pg_analyse/sql/contrib/index_health/sql/invalid_indexes.sql
pg_analyse/sql/contrib/index_health/sql/tables_with_missing_indexes.sql
pg_analyse/sql/contrib/index_health/sql/tables_without_primary_key.sql
pg_analyse/sql/contrib/index_health/sql/unused_indexes.sql
pg_analyse/sql/contrib/index_health/sql/ext/slowest_queries_by_total_execution_time.sql
pg_analyse-0.5.0.dist-info/AUTHORS
pg_analyse-0.5.0.dist-info/LICENSE
pg_analyse-0.5.0.dist-info/METADATA
pg_analyse-0.5.0.dist-info/WHEEL
pg_analyse-0.5.0.dist-info/entry_points.txt
pg_analyse-0.5.0.dist-info/top_level.txt
pg_analyse-0.5.0.dist-info/RECORD
