Metadata-Version: 2.1
Name: pg-analyse
Version: 0.5.0
Summary: Tools to gather useful information from PostgreSQL
Home-page: https://github.com/idlesign/pg_analyse
Author: Igor `idle sign` Starikov
Author-email: idlesign@yandex.ru
License: BSD 3-Clause License
Platform: UNKNOWN
Classifier: Development Status :: 4 - Beta
Classifier: Operating System :: OS Independent
Classifier: Programming Language :: Python
Classifier: Programming Language :: Python :: 3
Classifier: Programming Language :: Python :: 3.6
Classifier: Programming Language :: Python :: 3.7
Classifier: Programming Language :: Python :: 3.8
Classifier: License :: OSI Approved :: BSD License
Requires-Python: >=3.6
Provides-Extra: cli
Requires-Dist: click ; extra == 'cli'
Requires-Dist: tabulate ; extra == 'cli'
